CHANGELOG.rst
LICENSE
MANIFEST.in
README.rst
fedmsg_fasclient.py
python-fedmsg-fasclient.spec
setup.py
fedmsg.d/fasclient-example-config.py
fedmsg_fasclient.egg-info/PKG-INFO
fedmsg_fasclient.egg-info/SOURCES.txt
fedmsg_fasclient.egg-info/dependency_links.txt
fedmsg_fasclient.egg-info/entry_points.txt
fedmsg_fasclient.egg-info/requires.txt
fedmsg_fasclient.egg-info/top_level.txt