Metadata-Version: 1.0
Name: fedmsg-fasclient
Version: 0.6
Summary: A fedmsg consumer that runs the fasClient based on fedmsg FAS messages
Home-page: https://github.com/fedora-infra/fedmsg-fasclient
Author: Janez Nemanič, Ralph Bean and Pierre-Yves Chibon
Author-email: admin@fedoraproject.org
License: LGPLv2+
Platform: UNKNOWN
